lowcode_cli/common/__init__.py
lowcode_cli/common/jinja2/__init__.py
lowcode_cli/common/jinja2/filters/__init__.py
lowcode_cli/common/jinja2/handles/__init__.py
lowcode_cli/common/jsonschema/__init__.py
lowcode_cli/common/jsonschema/validators.py
lowcode_cli/conf/__init__.py
lowcode_cli/conf/settings.py
lowcode_cli/core/__init__.py
lowcode_cli/core/commands/__init__.py
lowcode_cli/core/commands/render.py
lowcode_cli/core/formater.py
lowcode_cli/core/renderer.py
lowcode_cli/manage.py
lowcode_cli/settings.default.yaml
lowcode_cli/tools/doc/__init__.py
lowcode_cli/tools/doc/markdown_to_schema.py
lowcode_cli/utils/__init__.py
lowcode_cli/utils/path.py
lowcode_cli-0.1.dist-info/entry_points.txt
lowcode_cli-0.1.dist-info/LICENSE
lowcode_cli-0.1.dist-info/WHEEL
lowcode_cli-0.1.dist-info/METADATA
lowcode_cli-0.1.dist-info/RECORD
